curioso/__init__.py
curioso/_cli.py
curioso/_utils.py
curioso/app.py
curioso-1.0.0rc0.dist-info/licenses/LICENSE
curioso-1.0.0rc0.dist-info/METADATA
curioso-1.0.0rc0.dist-info/WHEEL
curioso-1.0.0rc0.dist-info/entry_points.txt
curioso-1.0.0rc0.dist-info/top_level.txt
curioso-1.0.0rc0.dist-info/RECORD
