Metadata-Version: 2.4
Name: curioso
Version: 1.0.0rc0
Summary: Generates an operating system information report
Author-email: David Angarita <davidangarita.sistemas@gmail.com>
Maintainer-email: Andrew Pikul <ajpikul@gmail.com>
License: MIT License
Requires-Python: >=3.12
License-File: LICENSE
Requires-Dist: packaging>=25.0
Dynamic: license-file
